fontmapster/__init__.py
fontmapster/common/typevars.py
fontmapster/common/utils.py
fontmapster/main.py
fontmapster-0.1.0.dist-info/LICENSE
fontmapster-0.1.0.dist-info/METADATA
fontmapster-0.1.0.dist-info/WHEEL
fontmapster-0.1.0.dist-info/RECORD
